Tensorflow1XShenduXuexiMijiChuyi/README.md
Tensorflow1XShenduXuexiMijiChuyi/__init__.py
Tensorflow1XShenduXuexiMijiChuyi/__main__.py
Tensorflow1XShenduXuexiMijiChuyi/file.epub
Tensorflow1XShenduXuexiMijiChuyi/index.html
Tensorflow1XShenduXuexiMijiChuyi/css/__init__.py
Tensorflow1XShenduXuexiMijiChuyi/css/annotations.css
Tensorflow1XShenduXuexiMijiChuyi/css/main.css
Tensorflow1XShenduXuexiMijiChuyi/css/normalize.css
Tensorflow1XShenduXuexiMijiChuyi/css/popup.css
Tensorflow1XShenduXuexiMijiChuyi/font/__init__.py
Tensorflow1XShenduXuexiMijiChuyi/font/fontello.eot
Tensorflow1XShenduXuexiMijiChuyi/font/fontello.svg
Tensorflow1XShenduXuexiMijiChuyi/font/fontello.ttf
Tensorflow1XShenduXuexiMijiChuyi/font/fontello.woff
Tensorflow1XShenduXuexiMijiChuyi/img/__init__.py
Tensorflow1XShenduXuexiMijiChuyi/img/annotator-glyph-sprite.png
Tensorflow1XShenduXuexiMijiChuyi/img/annotator-icon-sprite.png
Tensorflow1XShenduXuexiMijiChuyi/img/apple-touch-icon.png
Tensorflow1XShenduXuexiMijiChuyi/img/cancelfullscreen.png
Tensorflow1XShenduXuexiMijiChuyi/img/close.png
Tensorflow1XShenduXuexiMijiChuyi/img/fullscreen.png
Tensorflow1XShenduXuexiMijiChuyi/img/loader.gif
Tensorflow1XShenduXuexiMijiChuyi/img/menu-icon.png
Tensorflow1XShenduXuexiMijiChuyi/img/save.png
Tensorflow1XShenduXuexiMijiChuyi/img/saved.png
Tensorflow1XShenduXuexiMijiChuyi/img/settings-s.png
Tensorflow1XShenduXuexiMijiChuyi/img/settings.png
Tensorflow1XShenduXuexiMijiChuyi/img/star.png
Tensorflow1XShenduXuexiMijiChuyi/js/__init__.py
Tensorflow1XShenduXuexiMijiChuyi/js/epub.js
Tensorflow1XShenduXuexiMijiChuyi/js/epub.min.js
Tensorflow1XShenduXuexiMijiChuyi/js/epub.min.map
Tensorflow1XShenduXuexiMijiChuyi/js/hooks.min.js
Tensorflow1XShenduXuexiMijiChuyi/js/hooks.min.map
Tensorflow1XShenduXuexiMijiChuyi/js/reader.js
Tensorflow1XShenduXuexiMijiChuyi/js/reader.js.map
Tensorflow1XShenduXuexiMijiChuyi/js/reader.min.js
Tensorflow1XShenduXuexiMijiChuyi/js/reader.min.map
Tensorflow1XShenduXuexiMijiChuyi/js/hooks/__init__.py
tensorflow_1_x_shendu_xuexi_miji_chuyi-2024.3.5.0.dist-info/METADATA
tensorflow_1_x_shendu_xuexi_miji_chuyi-2024.3.5.0.dist-info/WHEEL
tensorflow_1_x_shendu_xuexi_miji_chuyi-2024.3.5.0.dist-info/entry_points.txt
tensorflow_1_x_shendu_xuexi_miji_chuyi-2024.3.5.0.dist-info/top_level.txt
tensorflow_1_x_shendu_xuexi_miji_chuyi-2024.3.5.0.dist-info/RECORD
